{
  "area": "广东",
  "plans": [
    {
      "id": "telecom-广东-24GD100339",
      "name": "eSIM手表套餐9元（预付费）",
      "area": "广东",
      "price": 9.0,
      "data": 0.49,
      "generalData": 0.49,
      "directedData": 0,
      "voice": 5.0,
      "sms": "以官方详情为准",
      "broadband": "以官方详情为准",
      "audience": "适用于支持eSIM功能的手表类终端用户办理；不允许开副卡的单卡产品无法受理esim一号双终端业务",
      "contract": "24个月,到期后双方无异议，每次自动接续24个月",
      "source": "中国电信资费专区",
      "tags": [
        "套餐",
        "移网",
        "本省资费"
      ],
      "details": {
        "schemeId": "24GD100339",
        "tariffStandard": "9.00元/月",
        "onlineDate": "2024-01-01 00:00:00",
        "offlineDate": "2026-10-31 23:59:59",
        "category": "套餐",
        "sourceUrl": "https://gd.189.cn/support/fee/zone/index.html#/detail?report_no=24GD100339",
        "notes": "（1）新用户订购立即生效，当月费用全额收取，业务内容全部享受。老用户订购或变更次月生效。\r\n（2）套餐退订次月生效\r\n（3）受理入口：仅限支持esim的终端端内办理，受部分地市销售政策限制，部分地市对于本业务订购有套餐档位及其他条件限制，具体请洽当地10000号。",
        "applicableArea": "适用于支持eSIM功能的手表类终端用户办理；不允许开副卡的单卡产品无法受理esim一号双终端业务",
        "salesChannel": "线上及线下渠道",
        "validity": "24个月,到期后双方无异议，每次自动接续24个月",
        "networkRequirement": "无",
        "cancelMethod": "线上及线下渠道",
        "liability": "无",
        "overage": "国内流量0.03元/MB； 国内通话0.1元/分钟； 国内短/彩信0.1元/条。",
        "services": "国内接听免费，送来电显示、天翼云盘免费版、189免费邮箱。",
        "verified": true
      }
    },
    {
      "id": "telecom-广东-24GD100085",
      "name": "无忧卡（升级版）-10元",
      "area": "广东",
      "price": 10.0,
      "data": 1.0,
      "generalData": 1.0,
      "directedData": 0,
      "voice": 0.0,
      "sms": "以官方详情为准",
      "broadband": "以官方详情为准",
      "audience": "全网用户（深圳、佛山、江门、珠海、湛江、汕头、汕尾、潮州、惠州、揭阳、韶关、清远、中山用户，同一身份证在180天内，只可在5元无忧卡、10元无忧卡、39元暖心卡中任选办理1张）（广州用户暂不可办理）",
      "contract": "24个月，到期双方无异议自动续约24个月",
      "source": "中国电信资费专区",
      "tags": [
        "套餐",
        "移网",
        "本省资费"
      ],
      "details": {
        "schemeId": "24GD100085",
        "tariffStandard": "10.00元/月",
        "onlineDate": "2024-01-01 00:00:00",
        "offlineDate": "2028-06-30 23:59:59",
        "category": "套餐",
        "sourceUrl": "https://gd.189.cn/support/fee/zone/index.html#/detail?report_no=24GD100085",
        "notes": "",
        "applicableArea": "全网用户（深圳、佛山、江门、珠海、湛江、汕头、汕尾、潮州、惠州、揭阳、韶关、清远、中山用户，同一身份证在180天内，只可在5元无忧卡、10元无忧卡、39元暖心卡中任选办理1张）（广州用户暂不可办理）",
        "salesChannel": "线下渠道",
        "validity": "24个月，到期双方无异议自动续约24个月",
        "networkRequirement": "无",
        "cancelMethod": "线上及线下渠道",
        "liability": "无",
        "overage": "",
        "verified": true,
        "services": "一、含国内流量1GB，国内通话80分钟。国内接听免费，含来显和云盘、189邮箱。\r\n二、套外资费（国内）：1.流量：国内流量前167MB按0.03/MB收费达到167MB时赠送857MB流量，后续仍按上述规则收费（即每超出1GB按照5元/GB收费）；2.语音0.1元/分钟；3.短信 0.1元/条。国内”指中国内地，不含港澳台。\r\n三、新用户当月生效，当月套餐费、套餐内容按天折算，向上取整。老用户订购、变更、退订、次月生效，办理当月按原业务资费执行。\r\n四、广州用户自2026年4月10日起暂停办理。"
      }
    },
    {
      "id": "telecom-广东-24GD100340",
      "name": "eSIM手表套餐19元（预付费）",
      "area": "广东",
      "price": 19.0,
      "data": 1.0,
      "generalData": 1.0,
      "directedData": 0,
      "voice": 10.0,
      "sms": "以官方详情为准",
      "broadband": "以官方详情为准",
      "audience": "适用于支持eSIM功能的手表类终端用户办理；不允许开副卡的单卡产品无法受理esim一号双终端业务",
      "contract": "24个月,到期后双方无异议，每次自动接续24个月",
      "source": "中国电信资费专区",
      "tags": [
        "套餐",
        "移网",
        "本省资费"
      ],
      "details": {
        "schemeId": "24GD100340",
        "tariffStandard": "19.00元/月",
        "onlineDate": "2024-01-01 00:00:00",
        "offlineDate": "2026-10-31 23:59:59",
        "category": "套餐",
        "sourceUrl": "https://gd.189.cn/support/fee/zone/index.html#/detail?report_no=24GD100340",
        "notes": "（1）新用户订购立即生效，当月费用全额收取，业务内容全部享受。老用户订购或变更次月生效。\r\n（2）套餐退订次月生效，允许拆机。\r\n（3）受理入口：仅限支持esim的终端端内办理，受部分地市销售政策限制，部分地市对于本业务订购有套餐档位及其他条件限制，具体请洽当地10000号。",
        "applicableArea": "适用于支持eSIM功能的手表类终端用户办理；不允许开副卡的单卡产品无法受理esim一号双终端业务",
        "salesChannel": "线上及线下渠道",
        "validity": "24个月,到期后双方无异议，每次自动接续24个月",
        "networkRequirement": "无",
        "cancelMethod": "线上及线下渠道",
        "liability": "无",
        "overage": "国内流量0.03元/MB； 国内通话0.1元/分钟； 国内短/彩信0.1元/条。",
        "services": "国内接听免费，送来电显示、天翼云盘免费版、189免费邮箱。",
        "verified": true
      }
    },
    {
      "id": "telecom-广东-24GD100218",
      "name": "星卡29元（2022版）",
      "area": "广东",
      "price": 29.0,
      "data": 30.0,
      "generalData": 0,
      "directedData": 30.0,
      "voice": 0.0,
      "sms": "以官方详情为准",
      "broadband": "以官方详情为准",
      "audience": "公众用户（用户同一身份证在180天内，只可在29/39/59元星卡任选一张）",
      "contract": "24个月,到期后双方无异议，每次自动接续24个月",
      "source": "中国电信资费专区",
      "tags": [
        "套餐",
        "移网",
        "本省资费"
      ],
      "details": {
        "schemeId": "24GD100218",
        "tariffStandard": "29.00元/月",
        "onlineDate": "2021-12-23 00:00:00",
        "offlineDate": "2027-01-31 23:59:59",
        "category": "套餐",
        "sourceUrl": "https://gd.189.cn/support/fee/zone/index.html#/detail?report_no=24GD100218",
        "notes": "1、订购立即生效，当月套餐费及内容按天折算；变更退订次月生效\r\n2、当月套外流量消费600元的倍数则断网，次月开通，如申请继续使用则按套外资费收费。套餐外流量消费不含定向、闲时等流量包功能费\r\n3、定向流量为电信合作方提供，若合作关系发生变化，电信有权对相关内容进行调整或停止",
        "applicableArea": "公众用户（用户同一身份证在180天内，只可在29/39/59元星卡任选一张）",
        "salesChannel": "线下渠道",
        "validity": "24个月,到期后双方无异议，每次自动接续24个月",
        "networkRequirement": "无",
        "cancelMethod": "线上及线下渠道",
        "liability": "无",
        "overage": "1、国内通话：0.1元/分钟，不足1分钟部分按1分钟计\r\n2、国内短/彩信：发送0.1元/条，接收免费\r\n3、国内流量：5元/GB\r\n4、其余按标准资费计收\r\n注：国内指中国内地，不含港澳台地区",
        "services": "国内接听免费，赠送来显、天翼云盘免费版、189邮箱免费版，套餐包含定向流量可用于腾讯视频、抖音短视频等应用",
        "verified": true
      }
    },
    {
      "id": "telecom-广东-25GD101631",
      "name": "畅享29元套餐",
      "area": "广东",
      "price": 29.0,
      "data": 10.0,
      "generalData": 10.0,
      "directedData": 0.0,
      "voice": 0.0,
      "sms": "0",
      "broadband": "0",
      "audience": "公众",
      "contract": "24个月,到期后双方无异议，每次自动接续24个月",
      "source": "中国电信资费专区",
      "tags": [
        "套餐",
        "移网",
        "本省资费"
      ],
      "details": {
        "schemeId": "25GD101631",
        "tariffStandard": "29.00元/月",
        "onlineDate": "2025-07-21 00:00:00",
        "offlineDate": "2027-07-08 23:59:59",
        "category": "套餐",
        "sourceUrl": "https://gd.189.cn/support/fee/zone/index.html#/detail?report_no=25GD101631",
        "notes": "1、套餐中包含内容均适用于中国大陆境内，不含港澳台。2、手机上网流量不含 WLAN（Wi-Fi）上网。3、套餐所含流量适用于流量不清零规则，即当月套餐内剩余流量可结转至次月使用，次月底未使用完结转流量不再结转。4、手机上网当月套外流量消费600元倍数则断网，次月开通，如当月申请继续使用则按套外资费收费。5、新用户订购立即生效，当月套餐费、套餐内容按天折算，向上取整。老用户订购、变更、退订次月生效，办理当月按原资费执行。6、套餐有效期24个月，双方无异议自动续订24个月。",
        "applicableArea": "公众",
        "salesChannel": "线上及线下渠道",
        "validity": "24个月,到期后双方无异议，每次自动接续24个月",
        "networkRequirement": "无",
        "cancelMethod": "线上及线下渠道",
        "liability": "无",
        "overage": "国内：通话0.1元/分钟，短/彩信0.1元/条，手机上网流量不足167MB，按0.03元/MB计费，167MB到1GB免费，每1GB超出流量按上述规则计费，其他按标准资费",
        "services": "国内接听免费，送来电显示、天翼云盘免费版、189邮箱免费版",
        "verified": true
      }
    },
    {
      "id": "telecom-广东-24GD100224",
      "name": "星卡39元（2022版）",
      "area": "广东",
      "price": 39.0,
      "data": 35.0,
      "generalData": 5.0,
      "directedData": 30.0,
      "voice": 0.0,
      "sms": "以官方详情为准",
      "broadband": "以官方详情为准",
      "audience": "公众用户（用户同一身份证在180天内，只可在29/39/59元星卡任选一张）",
      "contract": "24个月,到期后双方无异议，每次自动接续24个月",
      "source": "中国电信资费专区",
      "tags": [
        "套餐",
        "移网",
        "本省资费"
      ],
      "details": {
        "schemeId": "24GD100224",
        "tariffStandard": "39.00元/月",
        "onlineDate": "2022-01-20 00:00:00",
        "offlineDate": "2027-01-31 23:59:59",
        "category": "套餐",
        "sourceUrl": "https://gd.189.cn/support/fee/zone/index.html#/detail?report_no=24GD100224",
        "notes": "1、订购立即生效，当月套餐费及内容按天折算；变更退订次月生效\r\n2、当月套外流量消费600元的倍数则断网，次月开通，如申请继续使用则按套外资费收费。套餐外流量消费不含定向、闲时等流量包功能费\r\n3、定向流量为电信合作方提供，若合作关系发生变化，电信有权对相关内容进行调整或停止",
        "applicableArea": "公众用户（用户同一身份证在180天内，只可在29/39/59元星卡任选一张）",
        "salesChannel": "线上及线下渠道",
        "validity": "24个月,到期后双方无异议，每次自动接续24个月",
        "networkRequirement": "无",
        "cancelMethod": "线上及线下渠道",
        "liability": "无",
        "overage": "",
        "services": "1、国内接听免费，赠送来显、天翼云盘免费版、189邮箱免费版，套餐包含定向流量可用于腾讯视频、抖音短视频等应用内容\r\n2.超出资费：\r\n1)国内通话：0.1元/分钟，不足1分钟部分按1分钟计\r\n2)国内短/彩信：发送0.1元/条，接收免费\r\n3)国内流量：5元/GB\r\n4) 其余按标准资费计收\r\n注：国内指中国内地，不含港澳台地区",
        "verified": true
      }
    },
    {
      "id": "telecom-广东-25GD101630",
      "name": "畅享39元套餐",
      "area": "广东",
      "price": 39.0,
      "data": 20.0,
      "generalData": 20.0,
      "directedData": 0,
      "voice": 0.0,
      "sms": "0",
      "broadband": "0",
      "audience": "公众",
      "contract": "24个月,到期后双方无异议，每次自动接续24个月",
      "source": "中国电信资费专区",
      "tags": [
        "套餐",
        "移网",
        "本省资费"
      ],
      "details": {
        "schemeId": "25GD101630",
        "tariffStandard": "39.00元/月",
        "onlineDate": "2025-07-21 00:00:00",
        "offlineDate": "2027-07-08 23:59:59",
        "category": "套餐",
        "sourceUrl": "https://gd.189.cn/support/fee/zone/index.html#/detail?report_no=25GD101630",
        "notes": "1、套餐中包含内容均适用于中国大陆境内，不含港澳台。2、手机上网流量不含 WLAN（Wi-Fi）上网。3、套餐所含流量适用于流量不清零规则，即当月套餐内剩余流量可结转至次月使用，次月底未使用完结转流量不再结转。4、手机上网当月套外流量消费600元倍数则断网，次月开通，如当月申请继续使用则按套外资费收费。5、新用户订购立即生效，当月套餐费、套餐内容按天折算，向上取整。老用户订购、变更、退订次月生效，办理当月按原资费执行。6、套餐有效期24个月，双方无异议自动续订24个月。",
        "applicableArea": "公众",
        "salesChannel": "线上及线下渠道",
        "validity": "24个月,到期后双方无异议，每次自动接续24个月",
        "networkRequirement": "无",
        "cancelMethod": "线上及线下渠道",
        "liability": "无",
        "overage": "国内：通话0.1元/分钟，短/彩信0.1元/条，手机上网流量不足167MB，按0.03元/MB计费，167MB到1GB免费，每1GB超出流量按上述规则计费，其他按标准资费",
        "services": "国内接听免费，送来电显示、天翼云盘免费版、189邮箱免费版",
        "verified": true
      }
    },
    {
      "id": "telecom-广东-24GD100581",
      "name": "5G畅享59元套餐",
      "area": "广东",
      "price": 59.0,
      "data": 10.0,
      "generalData": 10.0,
      "directedData": 0,
      "voice": 0.0,
      "sms": "以官方详情为准",
      "broadband": "以官方详情为准",
      "audience": "全网用户",
      "contract": "24个月,到期后双方无异议，每次自动接续24个月",
      "source": "中国电信资费专区",
      "tags": [
        "套餐",
        "移网",
        "本省资费"
      ],
      "details": {
        "schemeId": "24GD100581",
        "tariffStandard": "59.00元/月",
        "onlineDate": "2023-08-30 00:00:00",
        "offlineDate": "2026-10-31 23:59:59",
        "category": "套餐",
        "sourceUrl": "https://gd.189.cn/support/fee/zone/index.html#/detail?report_no=24GD100581",
        "notes": "",
        "applicableArea": "全网用户",
        "salesChannel": "线上及线下渠道",
        "validity": "24个月,到期后双方无异议，每次自动接续24个月",
        "networkRequirement": "无",
        "cancelMethod": "线上及线下渠道",
        "liability": "无",
        "overage": "国内：通话0.15元/分钟，短/彩信0.1元/条。流量前100MB按0.05元/MB收，达到100MB赠送924MB流量，后续按上述规则收，其他按标准资费,国内指中国内地，不含港澳台。",
        "services": "1、国内接听免费，送189邮箱、来显。2、新用户当月生效，当月套餐费、套餐内容按天折算，向上取整。3、老用户订购变更退订次月生效，办理当月按原资费。4、默认手机上网月套外流量消费600元则暂停上网服务（用户可按需变更，需另行申请其它档次的上网暂停服务），次月开通，申请继续使用按套外资费收费，套外流量消费不含用户订购流量包费。5、套餐含流量适用流量不清零规则，当月未使用完结转至次月，次月未使用完不结转。",
        "verified": true
      }
    },
    {
      "id": "telecom-广东-24GD100217",
      "name": "星卡流量版（59元）",
      "area": "广东",
      "price": 59.0,
      "data": 50.0,
      "generalData": 20.0,
      "directedData": 30.0,
      "voice": 0.0,
      "sms": "以官方详情为准",
      "broadband": "以官方详情为准",
      "audience": "公众用户（用户同一身份证在180天内，只可在29/39/59元星卡任选一张）",
      "contract": "24个月,到期后双方无异议，每次自动接续24个月",
      "source": "中国电信资费专区",
      "tags": [
        "套餐",
        "移网",
        "本省资费"
      ],
      "details": {
        "schemeId": "24GD100217",
        "tariffStandard": "59.00元/月",
        "onlineDate": "2021-11-11 00:00:00",
        "offlineDate": "2027-10-31 23:59:59",
        "category": "套餐",
        "sourceUrl": "https://gd.189.cn/support/fee/zone/index.html#/detail?report_no=24GD100217",
        "notes": "1、订购立即生效，当月套餐费及内容按天折算；变更退订次月生效。\r\n2、当月套外流量消费600元的倍数则断网，次月开通，如申请继续使用则按套外资费收费。套餐外流量消费不含定向、闲时等流量包功能费。\r\n3、定向流量为电信合作方提供，若合作关系发生变化，电信有权对相关内容进行调整或停止。",
        "applicableArea": "公众用户（用户同一身份证在180天内，只可在29/39/59元星卡任选一张）",
        "salesChannel": "线上及线下渠道",
        "validity": "24个月,到期后双方无异议，每次自动接续24个月",
        "networkRequirement": "无",
        "cancelMethod": "线上及线下渠道",
        "liability": "无",
        "overage": "",
        "services": "1、国内接听免费，赠送来显、天翼云盘免费版、189邮箱免费版，套餐包含定向流量可用于腾讯视频、抖音短视频等应用内容\r\n2.超出资费：\r\n1)国内通话：0.1元/分钟，不足1分钟部分按1分钟计\r\n2)国内短/彩信：发送0.1元/条，接收免费\r\n3)国内流量：5元/GB\r\n4) 其余按标准资费计收\r\n注：国内指中国内地，不含港澳台地区",
        "verified": true
      }
    },
    {
      "id": "telecom-广东-24GD100436",
      "name": "5G畅享79元套餐",
      "area": "广东",
      "price": 79.0,
      "data": 15.0,
      "generalData": 15.0,
      "directedData": 0,
      "voice": 0.0,
      "sms": "以官方详情为准",
      "broadband": "以官方详情为准",
      "audience": "全网用户",
      "contract": "24个月,到期后双方无异议，每次自动接续24个月",
      "source": "中国电信资费专区",
      "tags": [
        "套餐",
        "移网",
        "本省资费"
      ],
      "details": {
        "schemeId": "24GD100436",
        "tariffStandard": "79.00元/月",
        "onlineDate": "2023-08-30 00:00:00",
        "offlineDate": "2026-10-31 23:59:59",
        "category": "套餐",
        "sourceUrl": "https://gd.189.cn/support/fee/zone/index.html#/detail?report_no=24GD100436",
        "notes": "",
        "applicableArea": "全网用户",
        "salesChannel": "线下，万号",
        "validity": "24个月,到期后双方无异议，每次自动接续24个月",
        "networkRequirement": "无",
        "cancelMethod": "线上及线下渠道",
        "liability": "无",
        "overage": "国内:通话0.15元/分钟.短/ 彩信0.1元/条.流量前100MB按0.05/MB收,达100MB送924MB流量,后续仍按此规则收,其他按标准资费,国内指中国内地,不含港澳台",
        "services": "国内接听免费,送189邮箱.来显.新用户当月生效,当月套餐费.套餐内容按天折算向上取整.老用户订购变更退订次月生效,当月按原资费,手机上网当月套外流量消费600元倍数断网,次月开通,申请继续使用按套外资费收费,套外流量消费不含用户订购流量包费,该套餐包含流量适用流量不清零规则.套餐含流量当月未使用完结转至次月,次月未使用完不再结转",
        "verified": true
      }
    },
    {
      "id": "telecom-广东-24GD100824",
      "name": "5G畅享99元套餐202112",
      "area": "广东",
      "price": 99.0,
      "data": 20.0,
      "generalData": 20.0,
      "directedData": 0,
      "voice": 0.0,
      "sms": "以官方详情为准",
      "broadband": "以官方详情为准",
      "audience": "全网用户",
      "contract": "24个月，到期双方无异议自动续订24个月",
      "source": "中国电信资费专区",
      "tags": [
        "套餐",
        "移网",
        "本省资费"
      ],
      "details": {
        "schemeId": "24GD100824",
        "tariffStandard": "99.00元/月",
        "onlineDate": "2021-12-29 00:00:00",
        "offlineDate": "2027-01-31 23:59:59",
        "category": "套餐",
        "sourceUrl": "https://gd.189.cn/support/fee/zone/index.html#/detail?report_no=24GD100824",
        "notes": "",
        "applicableArea": "全网用户",
        "salesChannel": "线上及线下渠道",
        "validity": "24个月，到期双方无异议自动续订24个月",
        "networkRequirement": "无",
        "cancelMethod": "线上及线下渠道",
        "liability": "无",
        "overage": "",
        "services": "1.套餐超出资费：\r\n（1）套外流量：前100MB按0.03元/MB收费，达到100MB（3元）时，额外赠送用户924MB流量（即3元/1GB）;流量超过1GB时，仍按上述原则（即每超出1GB按照3元/1GB收费）收费，以此类推。\r\n（2）套外语音：当月国内通话超出对应套餐档位所包含分钟数后，按国内0.15元/分钟计收，不足1分钟按1分钟计。\r\n（3）国内短/彩信：0.1元/条\r\n2.国内流量适用范围：手机上网流量仅限中国大陆境内使用，可用于中国电信现有移动通信网络，不含WLAN（Wi-Fi）上网。\r\n具体使用规则以销售界面宣传及办理业务回执为准",
        "verified": true
      }
    },
    {
      "id": "telecom-广东-24GD100076",
      "name": "5G畅享129元套餐201910",
      "area": "广东",
      "price": 129.0,
      "data": 30.0,
      "generalData": 30.0,
      "directedData": 0,
      "voice": 0.0,
      "sms": "以官方详情为准",
      "broadband": "以官方详情为准",
      "audience": "全网用户",
      "contract": "24个月，到期双方无异议自动续订24个月",
      "source": "中国电信资费专区",
      "tags": [
        "套餐",
        "移网",
        "本省资费"
      ],
      "details": {
        "schemeId": "24GD100076",
        "tariffStandard": "129.00元/月",
        "onlineDate": "2024-01-01 00:00:00",
        "offlineDate": "2027-01-31 23:59:59",
        "category": "套餐",
        "sourceUrl": "https://gd.189.cn/support/fee/zone/index.html#/detail?report_no=24GD100076",
        "notes": "套餐有效期24个月，如双方无异议自动续订24个月",
        "applicableArea": "全网用户",
        "salesChannel": "线上及线下渠道",
        "validity": "24个月，到期双方无异议自动续订24个月",
        "networkRequirement": "无",
        "cancelMethod": "线上及线下渠道",
        "liability": "无",
        "overage": "",
        "services": "一、资费：国内接听免费，含来显和天翼云盘免费版、189免费邮箱\r\n二、套餐外资费（国内） 1.流量：前100MB按0.03元/MB收费，达到100MB时，额外赠送924MB流量；超出时仍按上述原则收费。2.语音0.15元/分钟。 3.短信 0.1元/条。“国内”指中国内地，不含港澳台地区\r\n三、手机上网当月套外流量消费600元的倍数则断网，次月开通，如客户当月申请继续使用，则按套外资费收费。套餐外流量消费不含用户订购的定向、闲时等流量包功能费。\r\n四、过渡期资费 1.订购当月按天折算费用，套餐内容按天折算，向上取整",
        "verified": true
      }
    },
    {
      "id": "telecom-广东-24GD100170",
      "name": "5G畅享169元套餐201910",
      "area": "广东",
      "price": 169.0,
      "data": 40.0,
      "generalData": 40.0,
      "directedData": 0,
      "voice": 0.0,
      "sms": "以官方详情为准",
      "broadband": "以官方详情为准",
      "audience": "全网用户",
      "contract": "24个月,到期后双方无异议，每次自动接续24个月",
      "source": "中国电信资费专区",
      "tags": [
        "套餐",
        "移网",
        "本省资费"
      ],
      "details": {
        "schemeId": "24GD100170",
        "tariffStandard": "169.00元/月",
        "onlineDate": "2024-01-01 00:00:00",
        "offlineDate": "2027-01-31 23:59:59",
        "category": "套餐",
        "sourceUrl": "https://gd.189.cn/support/fee/zone/index.html#/detail?report_no=24GD100170",
        "notes": "无",
        "applicableArea": "全网用户",
        "salesChannel": "线下，10000号",
        "validity": "24个月,到期后双方无异议，每次自动接续24个月",
        "networkRequirement": "无",
        "cancelMethod": "线上及线下渠道",
        "liability": "无",
        "overage": "",
        "services": "一、资费：国内接听免费，含来显和天翼云盘免费版、189免费邮箱\r\n二、套餐外资费（国内） 1.流量：前100MB按0.03元/MB收费，达到100MB时，额外赠送924MB流量；超出时仍按上述原则收费。2.语音0.15元/分钟。 3.短信 0.1元/条。“国内”指中国内地，不含港澳台地区\r\n三、手机上网当月套外流量消费600元的倍数则断网，次月开通，如客户当月申请继续使用，则按套外资费收费。套餐外流量消费不含用户订购的定向、闲时等流量包功能费。\r\n四、过渡期资费 1.订购当月按天折算费用，套餐内容按天折算，向上取整",
        "verified": true
      }
    },
    {
      "id": "telecom-广东-24GD100075",
      "name": "5G畅享199元套餐201910",
      "area": "广东",
      "price": 199.0,
      "data": 60.0,
      "generalData": 60.0,
      "directedData": 0,
      "voice": 0.0,
      "sms": "以官方详情为准",
      "broadband": "以官方详情为准",
      "audience": "全网用户",
      "contract": "24个月,到期后双方无异议，每次自动接续24个月",
      "source": "中国电信资费专区",
      "tags": [
        "套餐",
        "移网",
        "本省资费"
      ],
      "details": {
        "schemeId": "24GD100075",
        "tariffStandard": "199.00元/月",
        "onlineDate": "2024-01-01 00:00:00",
        "offlineDate": "2027-01-31 23:59:59",
        "category": "套餐",
        "sourceUrl": "https://gd.189.cn/support/fee/zone/index.html#/detail?report_no=24GD100075",
        "notes": "套餐有效期24个月，如双方无异议自动续订24个月",
        "applicableArea": "全网用户",
        "salesChannel": "线上及线下渠道",
        "validity": "24个月,到期后双方无异议，每次自动接续24个月",
        "networkRequirement": "无",
        "cancelMethod": "线上及线下渠道",
        "liability": "无",
        "overage": "",
        "services": "一、资费：国内接听免费，含来显和天翼云盘免费版、189免费邮箱\r\n二、套餐外资费（国内） 1.流量：前100MB按0.03元/MB收费，达到100MB时，额外赠送924MB流量；超出时仍按上述原则收费。2.语音0.15元/分钟。 3.短信 0.1元/条。“国内”指中国内地，不含港澳台地区\r\n三、手机上网当月套外流量消费600元的倍数则断网，次月开通，如客户当月申请继续使用，则按套外资费收费。套餐外流量消费不含用户订购的定向、闲时等流量包功能费。\r\n四、过渡期资费 1.订购当月按天折算费用，套餐内容按天折算，向上取整",
        "verified": true
      }
    },
    {
      "id": "telecom-广东-24GD100083",
      "name": "5G畅享239元套餐201910",
      "area": "广东",
      "price": 239.0,
      "data": 80.0,
      "generalData": 80.0,
      "directedData": 0,
      "voice": 0.0,
      "sms": "以官方详情为准",
      "broadband": "以官方详情为准",
      "audience": "全网用户",
      "contract": "24个月,到期后双方无异议，每次自动接续24个月",
      "source": "中国电信资费专区",
      "tags": [
        "套餐",
        "移网",
        "本省资费"
      ],
      "details": {
        "schemeId": "24GD100083",
        "tariffStandard": "239.00元/月",
        "onlineDate": "2024-01-01 00:00:00",
        "offlineDate": "2027-01-31 23:59:59",
        "category": "套餐",
        "sourceUrl": "https://gd.189.cn/support/fee/zone/index.html#/detail?report_no=24GD100083",
        "notes": "套餐有效期24个月，如双方无异议自动续订24个月",
        "applicableArea": "全网用户",
        "salesChannel": "线上及线下渠道",
        "validity": "24个月,到期后双方无异议，每次自动接续24个月",
        "networkRequirement": "无",
        "cancelMethod": "线上及线下渠道",
        "liability": "无",
        "overage": "",
        "services": "一、资费：国内接听免费，含来显和天翼云盘免费版、189免费邮箱\r\n二、套餐外资费（国内） 1.流量：前100MB按0.03元/MB收费，达到100MB时，额外赠送924MB流量；超出时仍按上述原则收费。2.语音0.15元/分钟。 3.短信 0.1元/条。“国内”指中国内地，不含港澳台地区\r\n三、手机上网当月套外流量消费600元的倍数则断网，次月开通，如客户当月申请继续使用，则按套外资费收费。套餐外流量消费不含用户订购的定向、闲时等流量包功能费。\r\n四、过渡期资费 1.订购当月按天折算费用，套餐内容按天折算，向上取整",
        "verified": true
      }
    },
    {
      "id": "telecom-广东-24GD100081",
      "name": "5G畅享299元套餐201910",
      "area": "广东",
      "price": 299.0,
      "data": 100.0,
      "generalData": 100.0,
      "directedData": 0,
      "voice": 0.0,
      "sms": "以官方详情为准",
      "broadband": "以官方详情为准",
      "audience": "全网用户",
      "contract": "24个月,到期后双方无异议，每次自动接续24个月",
      "source": "中国电信资费专区",
      "tags": [
        "套餐",
        "移网",
        "本省资费"
      ],
      "details": {
        "schemeId": "24GD100081",
        "tariffStandard": "299.00元/月",
        "onlineDate": "2024-01-01 00:00:00",
        "offlineDate": "2027-01-31 23:59:59",
        "category": "套餐",
        "sourceUrl": "https://gd.189.cn/support/fee/zone/index.html#/detail?report_no=24GD100081",
        "notes": "套餐有效期24个月，如双方无异议自动续订24个月",
        "applicableArea": "全网用户",
        "salesChannel": "线上及线下渠道",
        "validity": "24个月,到期后双方无异议，每次自动接续24个月",
        "networkRequirement": "无",
        "cancelMethod": "线上及线下渠道",
        "liability": "无",
        "overage": "",
        "services": "一、资费：国内接听免费，含来显和天翼云盘免费版、189免费邮箱\r\n二、套餐外资费（国内） 1.流量：前100MB按0.03元/MB收费，达到100MB时，额外赠送924MB流量；超出时仍按上述原则收费。2.语音0.15元/分钟。 3.短信 0.1元/条。“国内”指中国内地，不含港澳台地区\r\n三、手机上网当月套外流量消费600元的倍数则断网，次月开通，如客户当月申请继续使用，则按套外资费收费。套餐外流量消费不含用户订购的定向、闲时等流量包功能费。\r\n四、过渡期资费 1.订购当月按天折算费用，套餐内容按天折算，向上取整",
        "verified": true
      }
    },
    {
      "id": "telecom-广东-25GD102062",
      "name": "5G-A 399元套餐202503",
      "area": "广东",
      "price": 399.0,
      "data": 240.0,
      "generalData": 240.0,
      "directedData": 0,
      "voice": 0.0,
      "sms": "以官方详情为准",
      "broadband": "以官方详情为准",
      "audience": "广州",
      "contract": "24个月,到期后双方无异议，每次自动接续24个月",
      "source": "中国电信资费专区",
      "tags": [
        "套餐",
        "移网",
        "本省资费"
      ],
      "details": {
        "schemeId": "25GD102062",
        "tariffStandard": "399.00元/月",
        "onlineDate": "2025-04-21 00:00:00",
        "offlineDate": "2027-04-24 23:59:59",
        "category": "套餐",
        "sourceUrl": "https://gd.189.cn/support/fee/zone/index.html#/detail?report_no=25GD102062",
        "notes": "不支持改号业务，用户号码不可变更",
        "applicableArea": "广州",
        "salesChannel": "线下及线上",
        "validity": "24个月,到期后双方无异议，每次自动接续24个月",
        "networkRequirement": "无",
        "cancelMethod": "线下营业厅及10000号",
        "liability": "无",
        "overage": "",
        "services": "档位：399元；计费周期：周期型缴费：月；国内通用流量：240GB；国内语音拨打：2000分钟；国内语音接听：免费；网络权益（上下行峰值速率）：最高下行3Gbps，最高上行400Mbps；卫星权益：20分钟、20条短信；应用权益：漏话提醒、智能应答、视频彩铃、天翼云盘（个人版）、谢绝来电_天翼防骚扰。 ",
        "verified": true
      }
    },
    {
      "id": "telecom-广东-24GD100074",
      "name": "5G畅享399元套餐201910",
      "area": "广东",
      "price": 399.0,
      "data": 150.0,
      "generalData": 150.0,
      "directedData": 0,
      "voice": 0.0,
      "sms": "以官方详情为准",
      "broadband": "以官方详情为准",
      "audience": "全网用户",
      "contract": "24个月,到期后双方无异议，每次自动接续24个月",
      "source": "中国电信资费专区",
      "tags": [
        "套餐",
        "移网",
        "本省资费"
      ],
      "details": {
        "schemeId": "24GD100074",
        "tariffStandard": "399.00元/月",
        "onlineDate": "2024-01-01 00:00:00",
        "offlineDate": "2027-01-31 23:59:59",
        "category": "套餐",
        "sourceUrl": "https://gd.189.cn/support/fee/zone/index.html#/detail?report_no=24GD100074",
        "notes": "套餐有效期24个月，如双方无异议自动续订24个月",
        "applicableArea": "全网用户",
        "salesChannel": "线上及线下渠道",
        "validity": "24个月,到期后双方无异议，每次自动接续24个月",
        "networkRequirement": "无",
        "cancelMethod": "线上及线下渠道",
        "liability": "无",
        "overage": "",
        "services": "一、资费：国内接听免费，含来显和天翼云盘免费版、189免费邮箱\r\n二、套餐外资费（国内） 1.流量：前100MB按0.03元/MB收费，达到100MB时，额外赠送924MB流量；超出时仍按上述原则收费。2.语音0.15元/分钟。 3.短信 0.1元/条。“国内”指中国内地，不含港澳台地区\r\n三、手机上网当月套外流量消费600元的倍数则断网，次月开通，如客户当月申请继续使用，则按套外资费收费。套餐外流量消费不含用户订购的定向、闲时等流量包功能费。\r\n四、过渡期资费 1.订购当月按天折算费用，套餐内容按天折算，向上取整",
        "verified": true
      }
    },
    {
      "id": "telecom-广东-24GD100077",
      "name": "5G畅享599元套餐201910",
      "area": "广东",
      "price": 599.0,
      "data": 300.0,
      "generalData": 300.0,
      "directedData": 0,
      "voice": 0.0,
      "sms": "以官方详情为准",
      "broadband": "以官方详情为准",
      "audience": "全网用户",
      "contract": "24个月,到期后双方无异议，每次自动接续24个月",
      "source": "中国电信资费专区",
      "tags": [
        "套餐",
        "移网",
        "本省资费"
      ],
      "details": {
        "schemeId": "24GD100077",
        "tariffStandard": "599.00元/月",
        "onlineDate": "2024-01-01 00:00:00",
        "offlineDate": "2027-01-31 23:59:59",
        "category": "套餐",
        "sourceUrl": "https://gd.189.cn/support/fee/zone/index.html#/detail?report_no=24GD100077",
        "notes": "套餐有效期24个月，如双方无异议自动续订24个月",
        "applicableArea": "全网用户",
        "salesChannel": "线上及线下渠道",
        "validity": "24个月,到期后双方无异议，每次自动接续24个月",
        "networkRequirement": "无",
        "cancelMethod": "线上及线下渠道",
        "liability": "无",
        "overage": "",
        "services": "一、资费：国内接听免费，含来显和天翼云盘免费版、189免费邮箱\r\n二、套餐外资费（国内） 1.流量：前100MB按0.03元/MB收费，达到100MB时，额外赠送924MB流量；超出时仍按上述原则收费。2.语音0.15元/分钟。 3.短信 0.1元/条。“国内”指中国内地，不含港澳台地区\r\n三、手机上网当月套外流量消费600元的倍数则断网，次月开通，如客户当月申请继续使用，则按套外资费收费。套餐外流量消费不含用户订购的定向、闲时等流量包功能费。\r\n四、过渡期资费 1.订购当月按天折算费用，套餐内容按天折算，向上取整",
        "verified": true
      }
    }
  ]
}
